{
    "name": "Perfil",
    "fields": [
        {
            "fieldName": "perfil",
            "fieldType": "String"
        }
    ],
    "relationships": [
        {
            "relationshipType": "one-to-many",
            "otherEntityName": "candidato",
            "otherEntityRelationshipName": "perfil",
            "relationshipName": "candidato"
        },
        {
            "relationshipType": "one-to-many",
            "otherEntityName": "requerimiento",
            "otherEntityRelationshipName": "perfil",
            "relationshipName": "requerimiento"
        }
    ],
    "changelogDate": "20190708190629",
    "entityTableName": "perfil",
    "dto": "mapstruct",
    "pagination": "pagination",
    "service": "serviceImpl",
    "jpaMetamodelFiltering": true,
    "fluentMethods": true,
    "clientRootFolder": "",
    "applications": "*"
}